shuffl/__init__.py
shuffl/_analyze.py
shuffl/_deck.py
shuffl/_exceptions.py
shuffl/_models.py
shuffl/games.py
shuffle_kit-0.1.3.dist-info/LICENSE
shuffle_kit-0.1.3.dist-info/METADATA
shuffle_kit-0.1.3.dist-info/WHEEL
shuffle_kit-0.1.3.dist-info/RECORD
