Metadata-Version: 2.1
Name: shuffle-kit
Version: 0.1.3
Summary: 
Author: jmssnr
Author-email: maussner.johannes@gmail.com
Requires-Python: >=3.11,<4.0
Classifier: Programming Language :: Python :: 3
Classifier: Programming Language :: Python :: 3.11
Classifier: Programming Language :: Python :: 3.12
Requires-Dist: numpy (>=1.26.3,<2.0.0)
Project-URL: Documentation, https://jmssnr.github.io/shuffle-kit/
